pyBumpHunter/__init__.py
pyBumpHunter/bumphunter_1dim.py
pyBumpHunter/bumphunter_2dim.py
pyBumpHunter/util.py
pyBumpHunter/version.py
pyBumpHunter-0.4.2.dist-info/LICENSE
pyBumpHunter-0.4.2.dist-info/METADATA
pyBumpHunter-0.4.2.dist-info/WHEEL
pyBumpHunter-0.4.2.dist-info/top_level.txt
pyBumpHunter-0.4.2.dist-info/RECORD
