Metadata-Version: 2.1
Name: pyBumpHunter
Version: 0.4.2
Summary: Python implementation of the BumpHunter algorithm used by HEP community.
Home-page: https://github.com/scikit-hep/pyBumpHunter
Author: Louis VASLIN
Author-email: louis.vaslin@clermont.in2p3.fr
License: BSD-3-Clause
Classifier: Intended Audience :: Developers
Classifier: Intended Audience :: Science/Research
Classifier: License :: OSI Approved :: BSD License
Classifier: Programming Language :: Python :: 3
Classifier: Programming Language :: Python :: 3 :: Only
Classifier: Programming Language :: Python :: 3.6
Classifier: Programming Language :: Python :: 3.7
Classifier: Programming Language :: Python :: 3.8
Classifier: Programming Language :: Python :: 3.9
Classifier: Programming Language :: Python :: 3.10
Classifier: Topic :: Scientific/Engineering
Classifier: Topic :: Scientific/Engineering :: Information Analysis
Classifier: Topic :: Scientific/Engineering :: Mathematics
Classifier: Topic :: Scientific/Engineering :: Physics
Requires-Python: >=3.6
License-File: LICENSE
Requires-Dist: matplotlib
Requires-Dist: numpy (>=1.13.3)
Requires-Dist: scipy
Provides-Extra: example
Requires-Dist: jupyter ; extra == 'example'
Requires-Dist: uproot ; extra == 'example'
Provides-Extra: test
Requires-Dist: pytest ; extra == 'test'
Requires-Dist: uproot ; extra == 'test'
